higp_cext.cpython-38-x86_64-linux-gnu.so
higp/__init__.py
higp/modules.py
higp.libs/libgfortran-da86b648.so.5.0.0
higp.libs/libomp-420f2663.so
higp.libs/libopenblasp-r0-d83d6a43.3.28.so
higp.libs/libquadmath-aab14e96.so.0.0.0
higp-2025.11.3.dist-info/METADATA
higp-2025.11.3.dist-info/WHEEL
higp-2025.11.3.dist-info/top_level.txt
higp-2025.11.3.dist-info/RECORD
