Metadata-Version: 2.1
Name: higp
Version: 2025.11.3
Summary: HiGP is a high-performance Python package for using Gaussian processes (GPs) with large datasets.
Requires-Dist: numpy>=1.24.4
Requires-Dist: scipy>=1.3
Requires-Dist: torch>=1.3
